{
  "items": [
    {
      "name": "Cheesburger",
      "image": "/images/cheese.jpg",
      "desc": "Классический бургер с бифштексом из 100% говядины с маринованными огурчиками и свежей пшеничной булочкой.",
      "price": 11,
      "id": "001"
    },
    {
      "name": "Chicken Burger",
      "image": "/images/chicken.jpg",
      "desc": "Куриный бургер с добавлением расплавленного сыра, соуса Барбекю и листового салата.",
      "price": 10,
      "id": "002"
    },
    {
      "name": "Double Burger",
      "image": "/images/double.jpg",
      "desc": "Двойной гамбургер с бифштексом из 100% говядины и расплавленным сыром Чеддер и пряным соусом.",
      "price": 12,
      "id": "003"
    }
  ]
}
